LICENSE
sys_toolkit/__init__.py
sys_toolkit/base.py
sys_toolkit/clipboard/__init__.py
sys_toolkit/clipboard/base.py
sys_toolkit/clipboard/darwin.py
sys_toolkit/clipboard/wayland.py
sys_toolkit/clipboard/xclip.py
sys_toolkit/collection.py
sys_toolkit/configuration/__init__.py
sys_toolkit/configuration/base.py
sys_toolkit/configuration/directory.py
sys_toolkit/configuration/file.py
sys_toolkit/configuration/ini.py
sys_toolkit/configuration/json.py
sys_toolkit/configuration/yaml.py
sys_toolkit/constants.py
sys_toolkit/encoders.py
sys_toolkit/exceptions.py
sys_toolkit/fixtures.py
sys_toolkit/logger.py
sys_toolkit/modules.py
sys_toolkit/path.py
sys_toolkit/platform.py
sys_toolkit/process.py
sys_toolkit/subprocess.py
sys_toolkit/system/__init__.py
sys_toolkit/system/darwin.py
sys_toolkit/system/info.py
sys_toolkit/tests/__init__.py
sys_toolkit/tests/mock.py
sys_toolkit/tests/packaging.py
sys_toolkit/textfile.py
sys_toolkit/tmpdir/__init__.py
sys_toolkit/tmpdir/base.py
sys_toolkit/tmpdir/darwin.py
sys_toolkit-2.5.1.dist-info/LICENSE
sys_toolkit-2.5.1.dist-info/METADATA
sys_toolkit-2.5.1.dist-info/WHEEL
sys_toolkit-2.5.1.dist-info/entry_points.txt
sys_toolkit-2.5.1.dist-info/RECORD
