Metadata-Version: 2.1
Name: sys-toolkit
Version: 2.5.1
Summary: Classes for operating system utilities
Home-page: https://github.com/hile/sys-toolkit
License: BSD-3-Clause
Author: Ilkka Tuohela
Author-email: hile@iki.fi
Requires-Python: >=3.9,<4.0
Classifier: Environment :: Console
Classifier: License :: OSI Approved :: BSD License
Classifier: Operating System :: MacOS
Classifier: Operating System :: POSIX
Classifier: Operating System :: Unix
Classifier: Programming Language :: Python :: 3
Classifier: Programming Language :: Python :: 3.9
Classifier: Programming Language :: Python :: 3.10
Classifier: Programming Language :: Python :: 3.11
Classifier: Topic :: Utilities
Requires-Dist: PyYAML (>=6.0,<7.0)
Requires-Dist: inflection (>=0.5,<0.6)
